fish_reg/__init__.py
fish_reg/registration.py
fish_reg/run.py
fish_reg-0.0.2.dist-info/LICENSE
fish_reg-0.0.2.dist-info/METADATA
fish_reg-0.0.2.dist-info/WHEEL
fish_reg-0.0.2.dist-info/entry_points.txt
fish_reg-0.0.2.dist-info/top_level.txt
fish_reg-0.0.2.dist-info/RECORD
