Metadata-Version: 2.1
Name: fish-reg
Version: 0.0.2
Summary: fish video registration software
Home-page: https://github.com/meglaficus/fish_reg
Author: Jakob Meglič
Author-email: jakobmeglic123@gmail.com
License: Apache License Version 2.0, January 2004
Keywords: elastix,zebrafish,video,registration
License-File: LICENSE
Requires-Dist: tqdm
Requires-Dist: SimpleITK
Requires-Dist: SimpleITK-SimpleElastix
Requires-Dist: numpy
